{
  "main": {
    "id": "93ff55db6ee5c922",
    "type": "split",
    "children": [
      {
        "id": "8b61359874c44a05",
        "type": "tabs",
        "children": [
          {
            "id": "bf1e7a5147ecf581",
            "type": "leaf",
            "state": {
              "type": "empty",
              "state": {}
            }
          }
        ]
      }
    ],
    "direction": "vertical"
  },
  "left": {
    "id": "f803be4c00705ba5",
    "type": "split",
    "children": [
      {
        "id": "313eb26cf7ad9bc2",
        "type": "tabs",
        "children": [
          {
            "id": "adfcfd054796aa91",
            "type": "leaf",
            "state": {
              "type": "file-explorer",
              "state": {
                "sortOrder": "alphabetical"
              }
            }
          },
          {
            "id": "ab6863d0f111bf62",
            "type": "leaf",
            "state": {
              "type": "search",
              "state": {
                "query": "",
                "matchingCase": false,
                "explainSearch": false,
                "collapseAll": false,
                "extraContext": false,
                "sortOrder": "alphabetical"
              }
            }
          },
          {
            "id": "cd1e58fb3b8de66f",
            "type": "leaf",
            "state": {
              "type": "bookmarks",
              "state": {}
            }
          }
        ]
      }
    ],
    "direction": "horizontal",
    "width": 300
  },
  "right": {
    "id": "448f6ba2e7e674e7",
    "type": "split",
    "children": [
      {
        "id": "07017a1d5a234e18",
        "type": "tabs",
        "children": [
          {
            "id": "329be4db8ef4996e",
            "type": "leaf",
            "state": {
              "type": "backlink",
              "state": {
                "collapseAll": false,
                "extraContext": false,
                "sortOrder": "alphabetical",
                "showSearch": false,
                "searchQuery": "",
                "backlinkCollapsed": false,
                "unlinkedCollapsed": true
              }
            }
          },
          {
            "id": "024ee27ae7310edf",
            "type": "leaf",
            "state": {
              "type": "outgoing-link",
              "state": {
                "linksCollapsed": false,
                "unlinkedCollapsed": true
              }
            }
          },
          {
            "id": "53ff22fad9e5dfe6",
            "type": "leaf",
            "state": {
              "type": "tag",
              "state": {
                "sortOrder": "frequency",
                "useHierarchy": true
              }
            }
          },
          {
            "id": "4b2fe402dccd1f92",
            "type": "leaf",
            "state": {
              "type": "outline",
              "state": {}
            }
          }
        ]
      }
    ],
    "direction": "horizontal",
    "width": 300,
    "collapsed": true
  },
  "left-ribbon": {
    "hiddenItems": {
      "switcher:Ouvrir le sélecteur rapide": false,
      "graph:Ouvrir la vue graphique": false,
      "canvas:Créer une nouvelle toile": false,
      "daily-notes:Ouvrir la note quotidienne": false,
      "templates:Insérer le modèle": false,
      "command-palette:Ouvrir la palette de commandes": false
    }
  },
  "active": "bf1e7a5147ecf581",
  "lastOpenFiles": [
    "Sans titre.md",
    "Diagramme Relations",
    "Diagramme Objet",
    "Welcome.md",
    "Scénario",
    "Use Case",
    "Diagramme Séquence"
  ]
}